dataflake/fakeldap/__init__.py
dataflake/fakeldap/db.py
dataflake/fakeldap/op.py
dataflake/fakeldap/queryfilter.py
dataflake/fakeldap/queryparser.py
dataflake/fakeldap/utils.py
dataflake/fakeldap/tests/__init__.py
dataflake/fakeldap/tests/base.py
dataflake/fakeldap/tests/test_fakeldap.py
dataflake/fakeldap/tests/test_fakeldap_adddelete.py
dataflake/fakeldap/tests/test_fakeldap_bind.py
dataflake/fakeldap/tests/test_fakeldap_memberof.py
dataflake/fakeldap/tests/test_fakeldap_modify.py
dataflake/fakeldap/tests/test_fakeldap_search.py
dataflake/fakeldap/tests/test_op.py
dataflake/fakeldap/tests/test_queryfilter.py
dataflake/fakeldap/tests/test_queryparser.py
dataflake/fakeldap/tests/test_utils.py
dataflake_fakeldap-4.3.dist-info/licenses/LICENSE.txt
dataflake_fakeldap-4.3.dist-info/METADATA
dataflake_fakeldap-4.3.dist-info/WHEEL
dataflake_fakeldap-4.3.dist-info/top_level.txt
dataflake_fakeldap-4.3.dist-info/RECORD
