Metadata-Version: 2.4
Name: dataflake.fakeldap
Version: 4.3
Summary: Mocked-up LDAP connection library
Author-email: Jens Vagelpohl and contributors <jens@dataflake.org>
License-Expression: ZPL-2.1
Project-URL: Documentation, https://dataflakefakeldap.readthedocs.io
Project-URL: Issues, https://github.com/dataflake/dataflake.fakeldap/issues
Project-URL: Source, https://github.com/dataflake/dataflake.fakeldap
Project-URL: Changelog, https://dataflakefakeldap.readthedocs.io/en/latest/changes.html
Keywords: ldap,ldapv3
Classifier: Development Status :: 6 - Mature
Classifier: Intended Audience :: Developers
Classifier: Operating System :: OS Independent
Classifier: Programming Language :: Python
Classifier: Programming Language :: Python :: 3
Classifier: Programming Language :: Python :: 3 :: Only
Classifier: Programming Language :: Python :: 3.10
Classifier: Programming Language :: Python :: 3.11
Classifier: Programming Language :: Python :: 3.12
Classifier: Programming Language :: Python :: 3.13
Classifier: Programming Language :: Python :: 3.14
Classifier: Programming Language :: Python :: 3.15
Classifier: Programming Language :: Python :: Implementation :: CPython
Classifier: Topic :: Software Development :: Libraries :: Python Modules
Classifier: Topic :: Software Development :: Testing
Classifier: Topic :: System :: Systems Administration :: Authentication/Directory :: LDAP
Requires-Python: >=3.10
License-File: LICENSE.txt
Requires-Dist: python-ldap>=3.3
Provides-Extra: docs
Requires-Dist: Sphinx; extra == "docs"
Requires-Dist: furo; extra == "docs"
Provides-Extra: test
Requires-Dist: python-ldap; extra == "test"
Requires-Dist: volatildap; extra == "test"
Dynamic: license-file
